CHANGES.txt
LICENSE.txt
MANIFEST.in
README.rst
README_ja.rst
setup.py
googkit/__init__.py
googkit.egg-info/PKG-INFO
googkit.egg-info/SOURCES.txt
googkit.egg-info/dependency_links.txt
googkit.egg-info/entry_points.txt
googkit.egg-info/not-zip-safe
googkit.egg-info/requires.txt
googkit.egg-info/top_level.txt
googkit/commands/__init__.py
googkit/commands/apply_config.py
googkit/commands/build.py
googkit/commands/candidates.py
googkit/commands/command.py
googkit/commands/download.py
googkit/commands/init.py
googkit/commands/lint.py
googkit/commands/ready.py
googkit/commands/sequence.py
googkit/commands/setup.py
googkit/commands/update_deps.py
googkit/compat/__init__.py
googkit/compat/configparser/__init__.py
googkit/compat/unittest/__init__.py
googkit/compat/urllib/__init__.py
googkit/compat/urllib/request/__init__.py
googkit/lib/__init__.py
googkit/lib/argument.py
googkit/lib/argument_builder.py
googkit/lib/clone.py
googkit/lib/command_tree.py
googkit/lib/config.py
googkit/lib/dirutil.py
googkit/lib/environment.py
googkit/lib/error.py
googkit/lib/file.py
googkit/lib/help.py
googkit/lib/logutil.py
googkit/lib/path.py
googkit/lib/plugin.py
googkit/plugins/__init__.py
googkit_data/__init__.py
googkit_data/default.cfg
googkit_data/template/googkit.cfg
googkit_data/template/development/all_tests.html
googkit_data/template/development/index.html
googkit_data/template/development/style.css
googkit_data/template/development/js_dev/example.js
googkit_data/template/development/js_dev/example_test.html
googkit_data/template/development/js_dev/main.js
test/test_init.py