Metadata-Version: 1.1
Name: googkit
Version: 0.2.0
Summary: Easier way to develop your web app with Google Closure Library
Home-page: https://github.com/googkit/googkit
Author: cocopon & OrgaChem
Author-email: cocopon@me.com
License: MIT
Platform: UNKNOWN
Classifier: Development Status :: 4 - Beta
Classifier: License :: OSI Approved :: MIT License
Classifier: Topic :: Utilities
